{"name":"Eliminacion de un empleado","id":"eliminar-empleado;eliminacion-de-un-empleado","testSteps":[{"number":1,"description":"Dado que el usuario hace un llamado a la API de dummy restapiexample","duration":51,"startTime":"2022-08-21T14:36:08.064-05:00[America/Bogota]","result":"SUCCESS","precondition":false,"level":0},{"number":2,"description":"Cuando el realiza la peticion a la Api de \"Eliminar empleado\" con id \"2\" para eliminar","duration":4008,"startTime":"2022-08-21T14:36:08.119-05:00[America/Bogota]","result":"SUCCESS","precondition":false,"level":0,"children":[{"number":3,"description":"Andres consumir api con metodo delete","duration":3788,"startTime":"2022-08-21T14:36:08.335-05:00[America/Bogota]","result":"SUCCESS","precondition":false,"level":1,"children":[{"number":4,"description":"Andres executes a DELETE on the resource /api/v1/delete/2","duration":3736,"startTime":"2022-08-21T14:36:08.379-05:00[America/Bogota]","result":"SUCCESS","precondition":false,"level":2,"children":[{"number":5,"description":"DELETE http://dummy.restapiexample.com/api/v1/delete/2","duration":1,"startTime":"2022-08-21T14:36:12.114-05:00[America/Bogota]","result":"SUCCESS","restQuery":{"method":"DELETE","path":"http://dummy.restapiexample.com/api/v1/delete/2","content":"","contentType":"application/json","requestHeaders":"Accept\u003d*/*\n\t\t\t\tContent-Type\u003dapplication/json","requestCookies":"","responseHeaders":"Cache-Control: no-cache, private, max-age\u003d21600\nContent-Type: application/json\nDate: Sun, 21 Aug 2022 19:36:11 GMT\nDisplay: staticcontent_sol\nExpires: Mon, 22 Aug 2022 01:36:11 GMT\nHost-Header: c2hhcmVkLmJsdWVob3N0LmNvbQ\u003d\u003d\nResponse: 200\nServer: nginx\nVary: Accept-Encoding,Origin\nX-Endurance-Cache-Level: 2\nX-Ezoic-Cdn: Miss\nX-Middleton-Display: staticcontent_sol\nX-Middleton-Response: 200\nX-Nginx-Cache: WordPress\nX-Origin-Cache-Control: no-cache, private\nX-Ratelimit-Limit: 60\nX-Ratelimit-Remaining: 58\nX-Sol: pub_site\nContent-Length: 81","responseCookies":"","responseBody":"{\n    \"status\": \"success\",\n    \"data\": \"2\",\n    \"message\": \"Successfully! Record has been deleted\"\n}","statusCode":200},"precondition":false,"level":3}]}]}]},{"number":6,"description":"Entonces el podra visualizar una respuesta exitosa de eliminacion \"Successfully! Record has been deleted\"","duration":1029,"startTime":"2022-08-21T14:36:12.129-05:00[America/Bogota]","result":"SUCCESS","precondition":false,"level":0}],"userStory":{"id":"eliminar-empleado","storyName":"Eliminar empleado","displayName":"Eliminar empleado","path":"eliminar_empleado.feature","narrative":"  Yo como usuario\n  Necesito eliminar un empleado\n  Para borrar del sistema la informacion del empleado","type":"feature"},"featureTag":{"name":"Eliminar empleado","type":"feature","displayName":"Eliminar empleado"},"title":"Eliminacion de un empleado","description":"","tags":[{"name":"EliminarEmpleado","type":"tag","displayName":"EliminarEmpleado"},{"name":"Eliminar empleado","type":"feature","displayName":"Eliminar empleado"}],"startTime":"2022-08-21T14:36:07.774-05:00[America/Bogota]","duration":5395,"projectKey":"","isManualTestingUpToDate":false,"manual":false,"testSource":"Cucumber","actors":[{"name":"Andres","can":["call an API at http://dummy.restapiexample.com"]}],"result":"SUCCESS"}